jsonrpcstdio/__init__.py
jsonrpcstdio/errors.py
jsonrpcstdio/message.py
jsonrpcstdio/server.py
jsonrpcstdio-0.6.dist-info/LICENSE
jsonrpcstdio-0.6.dist-info/METADATA
jsonrpcstdio-0.6.dist-info/WHEEL
jsonrpcstdio-0.6.dist-info/top_level.txt
jsonrpcstdio-0.6.dist-info/RECORD
